heapitem.cpython-314-x86_64-linux-gnu.so
heapitem-0.1.6.dist-info/METADATA
heapitem-0.1.6.dist-info/WHEEL
heapitem-0.1.6.dist-info/top_level.txt
heapitem-0.1.6.dist-info/RECORD
heapitem-0.1.6.dist-info/licenses/LICENSE
