Metadata-Version: 2.4
Name: heapitem
Version: 0.1.6
Summary: Cython-accelerated heap item for password benchmarking
Author-email: Roberto Di Rosa <dirosa.2043388@studenti.uniroma1.it>
License: GNU LESSER GENERAL PUBLIC LICENSE
Project-URL: Homepage, https://github.com/BobTheBot988/heapitem
Project-URL: Issues, https://github.com/BobTheBot988/heapitem/issues
Classifier: License :: OSI Approved :: GNU Lesser General Public License v3 or later (LGPLv3+)
Classifier: Programming Language :: Python :: 3
Classifier: Programming Language :: Python :: Implementation :: CPython
Classifier: Operating System :: OS Independent
Requires-Python: >=3.8
License-File: LICENSE
Dynamic: license-file
